datascience_cookiecutter/__init__.py
datascience_cookiecutter/__main__.py
datascience_cookiecutter/folderbuilder.py
datascience_cookiecutter/templates.py
datascience_cookiecutter-0.4.3.dist-info/METADATA
datascience_cookiecutter-0.4.3.dist-info/WHEEL
datascience_cookiecutter-0.4.3.dist-info/entry_points.txt
datascience_cookiecutter-0.4.3.dist-info/RECORD
