Metadata-Version: 2.3
Name: datascience_cookiecutter
Version: 0.4.3
Project-URL: GitHub, https://github.com/raoulg/datascience-cookiecutter
Author-email: Raoul Grouls <Raoul.Grouls@han.nl>
License: MIT
Classifier: Development Status :: 4 - Beta
Classifier: Environment :: Console
Classifier: Intended Audience :: Developers
Classifier: License :: OSI Approved :: MIT License
Classifier: Operating System :: OS Independent
Classifier: Programming Language :: Python
Classifier: Topic :: Software Development
Classifier: Typing :: Typed
Requires-Python: >=3.9
Requires-Dist: click>=8.1.4
Requires-Dist: loguru>=0.7.0
Requires-Dist: pydantic>=2.0.2
Provides-Extra: lint
Requires-Dist: isort>=5.12.0; extra == 'lint'
Requires-Dist: pytest>=7.4.0; extra == 'lint'
Requires-Dist: ruff>=0.0.278; extra == 'lint'
